neptuno
