Metadata-Version: 1.1
Name: Neptuno2
Version: 1.2.3
Summary: A little set of utilities that Ender has been using in their web projects
Home-page: http://www.ender.es
Author: León Domingo
Author-email: leon.domingo@ender.es
License: UNKNOWN
Keywords: neptuno ender web
Platform: UNKNOWN
Classifier: Development Status :: 5 - Production/Stable
Classifier: Topic :: Utilities
